MANIFEST.in
README
redirector.py
requirements.txt
setup.cfg
setup.py
out_redirector.egg-info/PKG-INFO
out_redirector.egg-info/SOURCES.txt
out_redirector.egg-info/dependency_links.txt
out_redirector.egg-info/not-zip-safe
out_redirector.egg-info/top_level.txt
test/test_redirector.py