Metadata-Version: 1.1
Name: out-redirector
Version: 0.1.1
Summary: Manage and redirect standard output.
Home-page: https://github.com/pablerass/redirector
Author: Pablo Muñoz
Author-email: pablerass@gmail.com
License: LGPLv3
Platform: UNKNOWN
Classifier: Development Status :: 3 - Alpha
Classifier: Intended Audience :: Developers
Classifier: License :: OSI Approved :: GNU Lesser General Public License v3 (LGPLv3)
Classifier: Operating System :: OS Independent
